printhon/__init__.py
printhon/color.py
printhon/namevalue.py
printhon-0.1.8.dist-info/DESCRIPTION.rst
printhon-0.1.8.dist-info/METADATA
printhon-0.1.8.dist-info/RECORD
printhon-0.1.8.dist-info/WHEEL
printhon-0.1.8.dist-info/metadata.json
printhon-0.1.8.dist-info/top_level.txt
