Metadata-Version: 2.0
Name: printhon
Version: 0.1.8
Summary: Awesome python printor library
Home-page: https://github.com/nanopoteto/printhon
Author: nanopoteto
Author-email: ryota.natsume.26@gmail.com
License: MIT
Keywords: development
Platform: UNKNOWN
Classifier: Development Status :: 3 - Alpha
Classifier: Intended Audience :: Developers
Classifier: License :: OSI Approved :: MIT License
Classifier: Programming Language :: Python :: 3
Classifier: Programming Language :: Python :: 3.4
Classifier: Programming Language :: Python :: 3.5
Classifier: Programming Language :: Python :: 3.6
